.bumpversion.cfg
.travis.requirements.txt
.travis.script
.travis.yml
.virtualenv.dev-requirements.txt
.virtualenv.requirements.txt
LICENSE
MANIFEST.in
Makefile
README.md
setup.cfg
setup.py
azurectl/__init__.py
azurectl/app.py
azurectl/azurectl.py
azurectl/azurectl_exceptions.py
azurectl/cli.py
azurectl/defaults.py
azurectl/help.py
azurectl/logger.py
azurectl/version.py
azurectl.egg-info/PKG-INFO
azurectl.egg-info/SOURCES.txt
azurectl.egg-info/dependency_links.txt
azurectl.egg-info/entry_points.txt
azurectl.egg-info/not-zip-safe
azurectl.egg-info/requires.txt
azurectl.egg-info/top_level.txt
azurectl/account/__init__.py
azurectl/account/service.py
azurectl/account/setup.py
azurectl/commands/__init__.py
azurectl/commands/base.py
azurectl/commands/compute_data-disk.py
azurectl/commands/compute_endpoint.py
azurectl/commands/compute_image.py
azurectl/commands/compute_request.py
azurectl/commands/compute_reserved-ip.py
azurectl/commands/compute_shell.py
azurectl/commands/compute_vm.py
azurectl/commands/setup_account.py
azurectl/commands/storage_account.py
azurectl/commands/storage_container.py
azurectl/commands/storage_disk.py
azurectl/commands/storage_share.py
azurectl/config/__init__.py
azurectl/config/file_path.py
azurectl/config/parser.py
azurectl/instance/__init__.py
azurectl/instance/cloud_service.py
azurectl/instance/data_disk.py
azurectl/instance/endpoint.py
azurectl/instance/image.py
azurectl/instance/reserved_ip.py
azurectl/instance/virtual_machine.py
azurectl/management/__init__.py
azurectl/management/request_result.py
azurectl/storage/__init__.py
azurectl/storage/account.py
azurectl/storage/container.py
azurectl/storage/fileshare.py
azurectl/storage/page_blob.py
azurectl/storage/storage.py
azurectl/utils/__init__.py
azurectl/utils/collector.py
azurectl/utils/filetype.py
azurectl/utils/output.py
azurectl/utils/validations.py
azurectl/utils/xz.py
completion/azurectl.sh
package/spec-template